{"song_metadata": {"title": "bgm", "tempo": 103, "duration": 198.94, "difficulty": "normal", "note_count": 318}, "notes": [{"time": 0.348, "lane": 4}, {"time": 0.743, "lane": 1}, {"time": 1.904, "lane": 3}, {"time": 2.81, "lane": 0}, {"time": 3.088, "lane": 3}, {"time": 4.249, "lane": 1}, {"time": 5.132, "lane": 2}, {"time": 6.594, "lane": 1}, {"time": 7.779, "lane": 2}, {"time": 7.964, "lane": 2}, {"time": 8.382, "lane": 2}, {"time": 8.963, "lane": 1}, {"time": 9.729, "lane": 2}, {"time": 10.124, "lane": 4}, {"time": 10.333, "lane": 3}, {"time": 12.794, "lane": 1}, {"time": 15.023, "lane": 4}, {"time": 15.627, "lane": 2}, {"time": 17.183, "lane": 1}, {"time": 20.735, "lane": 3}, {"time": 21.293, "lane": 4}, {"time": 21.896, "lane": 1}, {"time": 22.198, "lane": 1}, {"time": 22.779, "lane": 2}, {"time": 24.218, "lane": 2}, {"time": 25.054, "lane": 0}, {"time": 26.773, "lane": 4}, {"time": 27.516, "lane": 2}, {"time": 27.794, "lane": 1}, {"time": 28.096, "lane": 3}, {"time": 28.653, "lane": 4}, {"time": 28.955, "lane": 1}, {"time": 29.164, "lane": 1}, {"time": 30.0, "lane": 0}, {"time": 30.418, "lane": 4}, {"time": 32.369, "lane": 4}, {"time": 33.367, "lane": 2}, {"time": 33.553, "lane": 1}, {"time": 34.737, "lane": 4}, {"time": 35.132, "lane": 2}, {"time": 36.014, "lane": 1}, {"time": 36.618, "lane": 4}, {"time": 37.198, "lane": 3}, {"time": 37.779, "lane": 4}, {"time": 38.081, "lane": 0}, {"time": 38.545, "lane": 1}, {"time": 38.963, "lane": 1}, {"time": 39.544, "lane": 3}, {"time": 42.191, "lane": 4}, {"time": 42.794, "lane": 0}, {"time": 44.257, "lane": 3}, {"time": 44.559, "lane": 4}, {"time": 45.14, "lane": 1}, {"time": 45.627, "lane": 3}, {"time": 46.324, "lane": 0}, {"time": 46.788, "lane": 3}, {"time": 47.206, "lane": 0}, {"time": 47.508, "lane": 2}, {"time": 47.787, "lane": 2}, {"time": 47.972, "lane": 1}, {"time": 48.855, "lane": 0}, {"time": 49.25, "lane": 3}, {"time": 49.551, "lane": 0}, {"time": 49.853, "lane": 2}, {"time": 50.712, "lane": 4}, {"time": 51.223, "lane": 1}, {"time": 51.618, "lane": 3}, {"time": 51.897, "lane": 0}, {"time": 52.198, "lane": 2}, {"time": 52.616, "lane": 4}, {"time": 52.779, "lane": 3}, {"time": 53.081, "lane": 0}, {"time": 53.522, "lane": 2}, {"time": 54.265, "lane": 4}, {"time": 54.544, "lane": 0}, {"time": 55.426, "lane": 4}, {"time": 55.914, "lane": 3}, {"time": 56.308, "lane": 1}, {"time": 56.912, "lane": 0}, {"time": 57.191, "lane": 3}, {"time": 57.4, "lane": 1}, {"time": 58.236, "lane": 4}, {"time": 58.654, "lane": 3}, {"time": 59.141, "lane": 2}, {"time": 60.024, "lane": 0}, {"time": 60.604, "lane": 3}, {"time": 61.022, "lane": 1}, {"time": 61.603, "lane": 2}, {"time": 62.09, "lane": 0}, {"time": 62.485, "lane": 4}, {"time": 62.973, "lane": 0}, {"time": 63.669, "lane": 4}, {"time": 63.971, "lane": 0}, {"time": 64.435, "lane": 3}, {"time": 64.83, "lane": 4}, {"time": 65.155, "lane": 0}, {"time": 65.434, "lane": 2}, {"time": 65.62, "lane": 3}, {"time": 65.921, "lane": 2}, {"time": 66.316, "lane": 0}, {"time": 66.502, "lane": 3}, {"time": 66.804, "lane": 0}, {"time": 66.966, "lane": 0}, {"time": 67.199, "lane": 2}, {"time": 67.779, "lane": 2}, {"time": 68.081, "lane": 1}, {"time": 68.383, "lane": 2}, {"time": 68.661, "lane": 0}, {"time": 69.521, "lane": 4}, {"time": 70.031, "lane": 0}, {"time": 70.426, "lane": 3}, {"time": 70.728, "lane": 4}, {"time": 70.914, "lane": 2}, {"time": 71.494, "lane": 1}, {"time": 71.912, "lane": 4}, {"time": 72.377, "lane": 3}, {"time": 72.795, "lane": 0}, {"time": 73.375, "lane": 0}, {"time": 73.863, "lane": 1}, {"time": 74.281, "lane": 2}, {"time": 74.745, "lane": 1}, {"time": 75.743, "lane": 0}, {"time": 76.231, "lane": 3}, {"time": 77.09, "lane": 0}, {"time": 77.485, "lane": 0}, {"time": 78.089, "lane": 0}, {"time": 78.576, "lane": 0}, {"time": 78.948, "lane": 2}, {"time": 79.552, "lane": 2}, {"time": 79.853, "lane": 4}, {"time": 80.132, "lane": 2}, {"time": 80.318, "lane": 2}, {"time": 80.62, "lane": 1}, {"time": 80.945, "lane": 0}, {"time": 85.426, "lane": 3}, {"time": 85.612, "lane": 4}, {"time": 87.771, "lane": 2}, {"time": 90.14, "lane": 1}, {"time": 90.302, "lane": 3}, {"time": 92.485, "lane": 2}, {"time": 94.436, "lane": 4}, {"time": 97.176, "lane": 2}, {"time": 98.081, "lane": 4}, {"time": 99.544, "lane": 2}, {"time": 99.73, "lane": 4}, {"time": 101.309, "lane": 2}, {"time": 101.889, "lane": 4}, {"time": 104.258, "lane": 1}, {"time": 105.326, "lane": 3}, {"time": 105.72, "lane": 1}, {"time": 107.787, "lane": 3}, {"time": 109.529, "lane": 0}, {"time": 110.132, "lane": 3}, {"time": 112.477, "lane": 2}, {"time": 113.383, "lane": 0}, {"time": 114.242, "lane": 1}, {"time": 114.753, "lane": 1}, {"time": 115.728, "lane": 4}, {"time": 116.611, "lane": 4}, {"time": 117.214, "lane": 3}, {"time": 117.516, "lane": 1}, {"time": 117.795, "lane": 2}, {"time": 118.561, "lane": 1}, {"time": 118.956, "lane": 4}, {"time": 119.56, "lane": 3}, {"time": 120.883, "lane": 4}, {"time": 121.626, "lane": 2}, {"time": 122.067, "lane": 4}, {"time": 122.485, "lane": 0}, {"time": 122.787, "lane": 2}, {"time": 123.252, "lane": 4}, {"time": 123.646, "lane": 0}, {"time": 124.227, "lane": 3}, {"time": 125.132, "lane": 4}, {"time": 125.411, "lane": 0}, {"time": 126.015, "lane": 1}, {"time": 126.549, "lane": 2}, {"time": 127.478, "lane": 4}, {"time": 127.779, "lane": 3}, {"time": 129.823, "lane": 4}, {"time": 130.125, "lane": 1}, {"time": 130.728, "lane": 4}, {"time": 131.286, "lane": 3}, {"time": 132.168, "lane": 0}, {"time": 132.47, "lane": 3}, {"time": 132.679, "lane": 0}, {"time": 133.654, "lane": 4}, {"time": 134.536, "lane": 4}, {"time": 134.815, "lane": 3}, {"time": 137.183, "lane": 3}, {"time": 137.369, "lane": 1}, {"time": 137.787, "lane": 4}, {"time": 138.321, "lane": 2}, {"time": 138.948, "lane": 2}, {"time": 139.25, "lane": 0}, {"time": 140.434, "lane": 0}, {"time": 140.922, "lane": 3}, {"time": 141.317, "lane": 0}, {"time": 141.897, "lane": 3}, {"time": 142.083, "lane": 4}, {"time": 142.478, "lane": 0}, {"time": 142.965, "lane": 3}, {"time": 143.36, "lane": 4}, {"time": 144.242, "lane": 2}, {"time": 145.125, "lane": 4}, {"time": 145.334, "lane": 0}, {"time": 145.728, "lane": 1}, {"time": 146.03, "lane": 4}, {"time": 146.309, "lane": 2}, {"time": 146.773, "lane": 2}, {"time": 147.772, "lane": 2}, {"time": 148.956, "lane": 2}, {"time": 150.024, "lane": 1}, {"time": 150.419, "lane": 0}, {"time": 151.301, "lane": 2}, {"time": 151.533, "lane": 0}, {"time": 151.882, "lane": 0}, {"time": 152.393, "lane": 3}, {"time": 152.787, "lane": 4}, {"time": 153.67, "lane": 2}, {"time": 153.879, "lane": 2}, {"time": 154.273, "lane": 0}, {"time": 154.715, "lane": 3}, {"time": 155.133, "lane": 4}, {"time": 156.015, "lane": 1}, {"time": 156.201, "lane": 3}, {"time": 156.595, "lane": 0}, {"time": 157.083, "lane": 0}, {"time": 157.478, "lane": 4}, {"time": 157.64, "lane": 2}, {"time": 157.965, "lane": 0}, {"time": 158.36, "lane": 2}, {"time": 158.569, "lane": 0}, {"time": 158.964, "lane": 2}, {"time": 159.242, "lane": 0}, {"time": 159.544, "lane": 2}, {"time": 160.125, "lane": 0}, {"time": 160.427, "lane": 4}, {"time": 160.729, "lane": 1}, {"time": 160.914, "lane": 2}, {"time": 161.797, "lane": 3}, {"time": 162.191, "lane": 1}, {"time": 162.493, "lane": 2}, {"time": 162.772, "lane": 0}, {"time": 163.074, "lane": 3}, {"time": 163.376, "lane": 4}, {"time": 163.654, "lane": 1}, {"time": 164.142, "lane": 1}, {"time": 164.838, "lane": 2}, {"time": 165.14, "lane": 0}, {"time": 165.419, "lane": 3}, {"time": 165.628, "lane": 0}, {"time": 166.023, "lane": 0}, {"time": 166.603, "lane": 4}, {"time": 167.207, "lane": 2}, {"time": 167.486, "lane": 0}, {"time": 167.787, "lane": 2}, {"time": 168.368, "lane": 3}, {"time": 168.972, "lane": 0}, {"time": 169.552, "lane": 0}, {"time": 169.831, "lane": 2}, {"time": 170.133, "lane": 0}, {"time": 170.342, "lane": 0}, {"time": 170.736, "lane": 0}, {"time": 170.899, "lane": 2}, {"time": 171.178, "lane": 4}, {"time": 171.595, "lane": 3}, {"time": 171.897, "lane": 0}, {"time": 172.478, "lane": 3}, {"time": 172.687, "lane": 2}, {"time": 173.058, "lane": 4}, {"time": 173.662, "lane": 2}, {"time": 174.544, "lane": 0}, {"time": 174.846, "lane": 4}, {"time": 175.032, "lane": 0}, {"time": 175.311, "lane": 2}, {"time": 175.914, "lane": 0}, {"time": 176.309, "lane": 0}, {"time": 176.611, "lane": 3}, {"time": 176.89, "lane": 0}, {"time": 177.377, "lane": 0}, {"time": 178.074, "lane": 0}, {"time": 178.376, "lane": 4}, {"time": 178.561, "lane": 0}, {"time": 178.956, "lane": 0}, {"time": 179.258, "lane": 4}, {"time": 179.537, "lane": 3}, {"time": 180.605, "lane": 0}, {"time": 181.603, "lane": 0}, {"time": 181.882, "lane": 2}, {"time": 182.486, "lane": 4}, {"time": 183.066, "lane": 3}, {"time": 183.368, "lane": 0}, {"time": 183.948, "lane": 0}, {"time": 184.25, "lane": 4}, {"time": 184.436, "lane": 1}, {"time": 184.854, "lane": 3}, {"time": 185.318, "lane": 3}, {"time": 186.108, "lane": 1}, {"time": 186.317, "lane": 0}, {"time": 186.805, "lane": 3}, {"time": 187.222, "lane": 0}, {"time": 187.687, "lane": 3}, {"time": 188.082, "lane": 1}, {"time": 188.685, "lane": 2}, {"time": 188.964, "lane": 4}, {"time": 189.15, "lane": 1}, {"time": 189.568, "lane": 0}, {"time": 190.055, "lane": 0}, {"time": 191.031, "lane": 2}, {"time": 191.309, "lane": 4}, {"time": 192.192, "lane": 0}, {"time": 192.493, "lane": 3}, {"time": 192.656, "lane": 1}, {"time": 193.074, "lane": 4}, {"time": 193.26, "lane": 2}, {"time": 193.654, "lane": 3}, {"time": 193.84, "lane": 0}]}